arinc424/__init__.py
arinc424/decoder.py
arinc424/record.py
arinc424/definitions/Airport.py
arinc424/definitions/AirportCommunication.py
arinc424/definitions/AirportGate.py
arinc424/definitions/AirwaysMarker.py
arinc424/definitions/Alternate.py
arinc424/definitions/CompanyRoute.py
arinc424/definitions/ControlledAirspace.py
arinc424/definitions/CruisingTables.py
arinc424/definitions/EnrouteAirways.py
arinc424/definitions/EnrouteAirwaysRestriction.py
arinc424/definitions/EnrouteCommunications.py
arinc424/definitions/FIRUIR.py
arinc424/definitions/FlightPlanning.py
arinc424/definitions/GLS.py
arinc424/definitions/GeoReferenceTable.py
arinc424/definitions/GridMORA.py
arinc424/definitions/Heliport.py
arinc424/definitions/HeliportCommunications.py
arinc424/definitions/HeliportTerminalWaypoint.py
arinc424/definitions/HoldingPattern.py
arinc424/definitions/LocalizerGlideslope.py
arinc424/definitions/LocalizerMarker.py
arinc424/definitions/MLS.py
arinc424/definitions/MSA.py
arinc424/definitions/NDBNavaid.py
arinc424/definitions/PathPoint.py
arinc424/definitions/PreferredRoute.py
arinc424/definitions/RestrictiveAirspace.py
arinc424/definitions/Runway.py
arinc424/definitions/SIDSTARApproach.py
arinc424/definitions/TAA.py
arinc424/definitions/VHFNavaid.py
arinc424/definitions/Waypoint.py
arinc424/definitions/__init__.py
arinc424-0.2.1.dist-info/METADATA
arinc424-0.2.1.dist-info/WHEEL
arinc424-0.2.1.dist-info/licenses/LICENCE.md
arinc424-0.2.1.dist-info/RECORD
