Metadata-Version: 2.3
Name: arinc424
Version: 0.2.1
Summary: A library for ARINC-424, the international standard file format for aircraft navigation data.
Project-URL: Homepage, https://github.com/jack-laverty/arinc424
Project-URL: Bug Tracker, https://github.com/jack-laverty/arinc424/issues
Author-email: Jack Laverty <jacktlaverty@gmail.com>
License-File: LICENCE.md
Classifier: License :: OSI Approved :: MIT License
Classifier: Operating System :: OS Independent
Classifier: Programming Language :: Python :: 3
Requires-Python: >=3.10
Requires-Dist: prettytable==3.9.0
Requires-Dist: termcolor==2.3.0
